preparer/__init__.py
preparer/preparers.py
preparer-0.1.0.dist-info/DESCRIPTION.rst
preparer-0.1.0.dist-info/METADATA
preparer-0.1.0.dist-info/RECORD
preparer-0.1.0.dist-info/WHEEL
preparer-0.1.0.dist-info/metadata.json
preparer-0.1.0.dist-info/top_level.txt
