Metadata-Version: 1.1
Name: preparer
Version: 0.1.0
Summary: Simple way to build a new dict based on fields declaration
Home-page: https://github.com/allisson/python-preparer
Author: Allisson Azevedo
Author-email: allisson@gmail.com
License: UNKNOWN
Platform: UNKNOWN
Classifier: Development Status :: 3 - Alpha
Classifier: Intended Audience :: Developers
Classifier: Programming Language :: Python :: 3.5
Classifier: Programming Language :: Python :: 3.6
Classifier: Topic :: Software Development :: Libraries
